Metadata-Version: 1.0
Name: BitSet
Version: 0.1.2
Summary: A Tool to see and use Binary data as Int
Home-page: https://gitee.com/lty2008one/BitSet
Author: lty2008one
Author-email: lty2008one@qq.com
License: MIT
Platform: UNKNOWN
